paper_manager/__init__.py
paper_manager/__init__.pyc
paper_manager/color.py
paper_manager/color.pyc
paper_manager/main.py
paper_manager/manager.py
paper_manager/manager.pyc
paper_manager/mycmd.py
paper_manager/mycmd.pyc
paper_manager/repository.py
paper_manager/repository.pyc
paper_manager-2.0.dist-info/DESCRIPTION.rst
paper_manager-2.0.dist-info/METADATA
paper_manager-2.0.dist-info/RECORD
paper_manager-2.0.dist-info/WHEEL
paper_manager-2.0.dist-info/entry_points.txt
paper_manager-2.0.dist-info/metadata.json
paper_manager-2.0.dist-info/top_level.txt
