Metadata-Version: 2.0
Name: paper-manager
Version: 2.0
Summary: No short description!
Home-page: https://github.com/applenob/paper_manager
Author: Kevin Chan
Author-email: applecer@pku.edu.cn
License: UNKNOWN
Download-URL: https://github.com/applenob/paper_manager/tarball/2018-04-14
Platform: Windows
Platform: MacOS
Platform: Unix
Classifier: Development Status :: 4 - Beta
Classifier: Intended Audience :: Education
Classifier: License :: OSI Approved :: MIT License
Classifier: Natural Language :: English
Classifier: Operating System :: Microsoft :: Windows
Classifier: Operating System :: MacOS
Classifier: Operating System :: Unix
Classifier: Programming Language :: Python :: 2.7
Classifier: Programming Language :: Python :: 3
Classifier: Programming Language :: Python :: 3.3
Classifier: Programming Language :: Python :: 3.4
Classifier: Programming Language :: Python :: 3.5
Classifier: Programming Language :: Python :: 3.6
Requires-Dist: colorama
Requires-Dist: terminaltables
